MANIFEST.in
README.md
setup.cfg
setup.py
flask_ptrans/__init__.py
flask_ptrans/ptrans.py
flask_ptrans.egg-info/PKG-INFO
flask_ptrans.egg-info/SOURCES.txt
flask_ptrans.egg-info/dependency_links.txt
flask_ptrans.egg-info/entry_points.txt
flask_ptrans.egg-info/requires.txt
flask_ptrans.egg-info/top_level.txt
flask_ptrans/scripts/__init__.py
flask_ptrans/scripts/aggregate_json.py
flask_ptrans/scripts/check_templates.py
flask_ptrans/scripts/list_untranslated_strings.py
flask_ptrans/scripts/pseudolocalise.py
flask_ptrans/scripts/resolve_json_conflicts.py