Metadata-Version: 1.1
Name: flask-ptrans
Version: 0.8
Summary: Flask extension for localisation of templates from JSON files
Home-page: https://github.com/Skyscanner/flask-ptrans
Author: Peter Harris
Author-email: peter.harris@skyscanner.net
License: Apache License v2
Download-URL: https://github.com/Skyscanner/flask-ptrans/tarball/0.8
Keywords: localisation,jinja2,flask,pootle
Platform: UNKNOWN
Classifier: Development Status :: 4 - Beta
Classifier: Framework :: Flask
Classifier: Intended Audience :: Developers
Classifier: Programming Language :: Python :: 2.7
Classifier: Programming Language :: Python :: 3
